grid_apps/__init__.py
grid_apps/_version.py
grid_apps/block_model_to_octree/__init__.py
grid_apps/block_model_to_octree/driver.py
grid_apps/block_model_to_octree/options.py
grid_apps/block_models/__init__.py
grid_apps/block_models/driver.py
grid_apps/block_models/options.py
grid_apps/octree_creation/__init__.py
grid_apps/octree_creation/driver.py
grid_apps/octree_creation/options.py
grid_apps/utils.py
grid_apps-assets/__init__.py
grid_apps-assets/uijson/block_model_to_octree.ui.json
grid_apps-assets/uijson/block_models.ui.json
grid_apps-assets/uijson/octree_mesh.ui.json
grid_apps-0.1.0.dist-info/METADATA
grid_apps-0.1.0.dist-info/WHEEL
grid_apps-0.1.0.dist-info/licenses/LICENSE
grid_apps-0.1.0.dist-info/licenses/docs/source/THIRD_PARTY_SOFTWARE.rst
grid_apps-0.1.0.dist-info/RECORD
