Metadata-Version: 2.4
Name: grid-apps
Version: 0.1.0
Summary: Grid creation and manipulation using GEOH5 format.
License-Expression: MIT
License-File: LICENSE
License-File: docs/source/THIRD_PARTY_SOFTWARE.rst
Keywords: geology,geophysics,earth sciences
Author: Mira Geoscience
Author-email: support@mirageoscience.com
Maintainer: Benjamin Kary
Maintainer-email: benjamink@mirageoscience.com
Requires-Python: >=3.10,<4.0
Classifier: Development Status :: 2 - Pre-Alpha
Classifier: Intended Audience :: Science/Research
Classifier: Natural Language :: English
Classifier: Operating System :: MacOS
Classifier: Operating System :: Microsoft :: Windows
Classifier: Operating System :: POSIX
Classifier: Operating System :: Unix
Classifier: Programming Language :: Python
Classifier: Programming Language :: Python :: 3
Classifier: Programming Language :: Python :: 3.10
Classifier: Programming Language :: Python :: 3.11
Classifier: Programming Language :: Python :: 3.12
Classifier: Programming Language :: Python :: 3.13
Classifier: Programming Language :: Python :: 3.14
Classifier: Topic :: Scientific/Engineering
Classifier: Topic :: Scientific/Engineering :: Mathematics
Classifier: Topic :: Scientific/Engineering :: Physics
Requires-Dist: discretize (>=0.11.0,<0.12.dev)
Requires-Dist: geoapps-utils (>=0.6.0b2,<0.7.dev0)
Requires-Dist: geoh5py (>=0.12.0b5,<0.13.dev0)
Requires-Dist: numpy (>=1.26.0,<1.27.0)
Requires-Dist: pydantic (>=2.5.2,<3.0.0)
Requires-Dist: scipy (>=1.14.0,<1.15.0)
Project-URL: Documentation, https://mirageoscience-grid-apps.readthedocs-hosted.com/
Project-URL: Homepage, https://www.mirageoscience.com/mining-industry-software/python-integration/
Project-URL: Repository, https://github.com/MiraGeoscience/grid-apps
